examples/ex0.py
examples/ex1.py
examples/ex2.py
examples/ex3.py
simsig/__init__.py
simsig/simsig.py
simsig-2.0.0.dist-info/licenses/LICENSE
tests/test_simsig.py
simsig-2.0.0.dist-info/METADATA
simsig-2.0.0.dist-info/WHEEL
simsig-2.0.0.dist-info/top_level.txt
simsig-2.0.0.dist-info/RECORD
