Metadata-Version: 2.4
Name: simsig
Version: 2.0.0
Summary: simsig: a simple but powerful thread-safe, and async-aware signal handling framework for Python
Author-email: Alex Semenyaka <alex.semenyaka@gmail.com>
License: MIT
Project-URL: Homepage, https://pypi.org/project/simsig/
Project-URL: Repository, https://github.com/alexsemenyaka/simsig
Keywords: signals
Classifier: Programming Language :: Python :: 3
Classifier: License :: OSI Approved :: MIT License
Classifier: Operating System :: OS Independent
Requires-Python: >=3.8
License-File: LICENSE
Dynamic: license-file
